blueprints/app/wsgi.tt.py
blueprints/app/[[ app_name ]]/__init__.py
blueprints/app/[[ app_name ]]/app.py
blueprints/app/[[ app_name ]]/routes.py
blueprints/app/[[ app_name ]]/cl/__init__.tt.py
blueprints/app/[[ app_name ]]/config/__init__.py
blueprints/app/[[ app_name ]]/config/app.tt.py
blueprints/app/[[ app_name ]]/config/database.tt.py
blueprints/app/[[ app_name ]]/config/session.py
blueprints/app/[[ app_name ]]/config/storage.py
blueprints/app/[[ app_name ]]/initializers/1_app.tt.py
blueprints/app/[[ app_name ]]/initializers/2_database.py
blueprints/app/[[ app_name ]]/initializers/__init__.py
blueprints/app/[[ app_name ]]/initializers/error_handlers.py
blueprints/app/[[ app_name ]]/mailers/__init__.py
blueprints/app/[[ app_name ]]/mailers/mailer.py
blueprints/app/[[ app_name ]]/models/__init__.py
blueprints/app/[[ app_name ]]/models/base.py
blueprints/app/[[ app_name ]]/models/concerns/__init__.py
blueprints/app/[[ app_name ]]/models/concerns/timestamped.tt.py
blueprints/app/[[ app_name ]]/views/__init__.py
blueprints/app/[[ app_name ]]/views/app.tt.py
blueprints/app/[[ app_name ]]/views/page.py
blueprints/app/[[ app_name ]]/views/concerns/__init__.py
blueprints/app/[[ app_name ]]/views/concerns/db_connection.tt.py
blueprints/app/[[ app_name ]]/views/concerns/security_headers.py
blueprints/app/tests/conftest.py
blueprints/auth/routes.tt.py
blueprints/auth/[[ app_name ]]/app.append.py
blueprints/auth/[[ app_name ]]/cl/__init__.append.py
blueprints/auth/[[ app_name ]]/cl/auth.tt.py
blueprints/auth/[[ app_name ]]/config/app.append.py
blueprints/auth/[[ app_name ]]/config/auth.py
blueprints/auth/[[ app_name ]]/mailers/auth.py
blueprints/auth/[[ app_name ]]/models/__init__.append.py
blueprints/auth/[[ app_name ]]/models/user.py
blueprints/auth/[[ app_name ]]/models/concerns/authenticable.tt.py
blueprints/auth/[[ app_name ]]/views/app.append.py
blueprints/auth/[[ app_name ]]/views/app.prepend.py
blueprints/auth/[[ app_name ]]/views/concerns/load_user.tt.py
proper-0.2.dist-info/METADATA
proper-0.2.dist-info/WHEEL
proper-0.2.dist-info/entry_points.txt
proper-0.2.dist-info/top_level.txt
proper-0.2.dist-info/RECORD
