Metadata-Version: 2.1
Name: proper
Version: 0.2
Summary: A web framework optimized for programmer happiness
Author-email: Juan-Pablo Scaletti <juanpablo@jpscaletti.com>
License: Copyright (c) 2019 Juan-Pablo Scaletti
Project-URL: homepage, https://proper.scaletti.dev/
Project-URL: repository, https://github.com/jpsca/proper
Project-URL: documentation, https://proper.scaletti.dev/
Classifier: Development Status :: 4 - Beta
Classifier: Environment :: Web Environment
Classifier: Intended Audience :: Developers
Classifier: License :: OSI Approved :: MIT License
Classifier: Programming Language :: Python :: 3 :: Only
Classifier: Programming Language :: Python :: 3.10
Classifier: Programming Language :: Python :: 3.11
Classifier: Programming Language :: Python :: 3.12
Classifier: Typing :: Typed
Requires-Python: >=3.10
Requires-Dist: inflection >=0.5.1
Requires-Dist: isort >=5.0
Requires-Dist: itsdangerous >=1.1
Requires-Dist: jinjax >=0.30
Requires-Dist: mailshake
Requires-Dist: markupsafe >=2.0
Requires-Dist: passlib >=1.7
Requires-Dist: peewee >=3.15
Requires-Dist: peewee-migrate <2,>=1.12.1
Requires-Dist: proper-cli >=1.2
Requires-Dist: tomlkit >=0.12.4
Requires-Dist: traceback-with-variables ==2.0.4
Requires-Dist: uwsgi >=2.0
Provides-Extra: dev
Requires-Dist: ipdb >=0.13 ; extra == 'dev'
Requires-Dist: pyright >=1.1 ; extra == 'dev'
Requires-Dist: pre-commit ; extra == 'dev'
Requires-Dist: ruff >=0.2.0 ; extra == 'dev'
Provides-Extra: test
Requires-Dist: pytest >=7.2 ; extra == 'test'
Requires-Dist: pytest-cov ; extra == 'test'
Requires-Dist: tox ; extra == 'test'
Requires-Dist: image-processing-egg ; extra == 'test'
Requires-Dist: poyo ; extra == 'test'
